{
  "schemaVersion": 3,
  "builtAt": "2026-06-01T20:23:32.834Z",
  "bizId": "ye-wu-yi",
  "keyVersion": "v1",
  "wasmObfuscated": true,
  "summary": {
    "totalFiles": 4,
    "totalSizeBytes": 181976,
    "prefixes": [
      "clinics/"
    ]
  },
  "search": {
    "enabled": true,
    "tier": 1,
    "entryCount": 5
  },
  "manifest": {
    "filename": "500e6b62ff67a81b97a8e79492f0448402556ae77b8b9acb2fc82cdbdeada528.enc",
    "algorithm": "aes-256-gcm",
    "ivBase64": "zcz8dFBtuiw6BYVO",
    "tagBase64": "l/X9pKYeWlIW5EeRmTmkrA==",
    "ivLen": 12,
    "tagLen": 16,
    "plaintextLen": 1523,
    "ciphertextLen": 1523
  },
  "wasm": {
    "filename": "8586e2df4bfd384fd10e770f9eee68944c5c33bc67215ea5c635720c2804898e.enc",
    "algorithm": "aes-256-gcm",
    "ivBase64": "qr16Hf/o3XP7XuZz",
    "tagBase64": "3iRxfzaBb7Fls5QRYCa8fA==",
    "ivLen": 12,
    "tagLen": 16,
    "plaintextLen": 29404,
    "ciphertextLen": 29404
  },
  "anchors": [
    {
      "index": 2,
      "filename": "afee58fdb922126f2afb5424c50b906952455fa69d3b4ddcac75bd20d85ad664.enc"
    },
    {
      "index": 3,
      "filename": "8e93c75a84a3e3ceb5c8c3be75ad47c908c4cd871852f94850d29232ce509560.enc"
    },
    {
      "index": 4,
      "filename": "9ab7c750c829efacf9f16431e4f82cf76602c5853e0bdcee6d2794022a830e4b.enc"
    }
  ]
}